autopytest/__init__.py
autopytest/autotest.py
autopytest/cli.py
autopytest/config.py
autopytest/file.py
autopytest/source.py
autopytest/strategy.py
autopytest/runners/__init__.py
autopytest/runners/pytest.py
autopytest-0.0.10.dist-info/METADATA
autopytest-0.0.10.dist-info/WHEEL
autopytest-0.0.10.dist-info/entry_points.txt
autopytest-0.0.10.dist-info/licenses/LICENSE
autopytest-0.0.10.dist-info/RECORD
