Metadata-Version: 2.1
Name: autopytest
Version: 0.0.10
Summary: Autotest python code
Project-URL: Homepage, https://github.com/davidjrice/autopytest
Project-URL: Bug Tracker, https://github.com/davidjrice/autopytest/issues
Author-email: David Rice <me@davidjrice.co.uk>
License: MIT License
License-File: LICENSE
Classifier: License :: OSI Approved :: MIT License
Classifier: Operating System :: OS Independent
Classifier: Programming Language :: Python :: 3
Requires-Python: >=3.10
Requires-Dist: packaging==23.2
Requires-Dist: toml==0.10.2; python_version < '3.11'
Requires-Dist: typing-extensions==4.8.0; python_version < '3.11'
Requires-Dist: watchdog==3.0.0
Provides-Extra: dev
Requires-Dist: black==23.11.0; extra == 'dev'
Requires-Dist: codespell==2.2.6; extra == 'dev'
Requires-Dist: refurb==1.24.0; extra == 'dev'
Requires-Dist: ruff==0.1.6; extra == 'dev'
Requires-Dist: tox==4.11.3; extra == 'dev'
Requires-Dist: types-toml==0.10.8.7; extra == 'dev'
